torch_bspline/__about__.py
torch_bspline/__init__.py
torch_bspline/bspline.py
torch_bspline/functions.py
torch_bspline/tensor_basis.py
torch_bspline/tensor_grid.py
torch_bspline-0.1.3.dist-info/METADATA
torch_bspline-0.1.3.dist-info/WHEEL
torch_bspline-0.1.3.dist-info/RECORD
